protoconfloader/agent/api/proto/v1/__init__.py
protoconfloader/agent/api/proto/v1/protoconf_service.proto
protoconfloader/agent/api/proto/v1/protoconf_service_pb2.py
protoconfloader/agent/api/proto/v1/protoconf_service_pb2_grpc.py
protoconfloader/protoconfloader.py
protoconfloader-0.1.1.dist-info/LICENSE
protoconfloader-0.1.1.dist-info/METADATA
protoconfloader-0.1.1.dist-info/WHEEL
protoconfloader-0.1.1.dist-info/RECORD
