Metadata-Version: 2.1
Name: protoconfloader
Version: 0.1.1
Summary: 
Author: Aviv Laufer
Author-email: aviv.laufer@gmail.com
Requires-Python: >=3.11,<4.0
Classifier: Programming Language :: Python :: 3
Classifier: Programming Language :: Python :: 3.11
Classifier: Programming Language :: Python :: 3.12
Requires-Dist: aiofiles (>=24.1.0,<25.0.0)
Requires-Dist: asyncio (>=3.4.3,<4.0.0)
Requires-Dist: grpcio (>=1.65.5,<2.0.0)
Requires-Dist: grpcio-tools (>=1.65.5,<2.0.0)
Requires-Dist: grpclib (>=0.4.7,<0.5.0)
Requires-Dist: protobuf (>=5.27.1,<6.0.0)
Requires-Dist: watchdog (>=4.0.2,<5.0.0)
